telomerecat/__init__.py
telomerecat/bam2length.py
telomerecat/bam2telbam.py
telomerecat/core.py
telomerecat/csv2length.py
telomerecat/telbam2length.py
telomerecat/version.py
telomerecat-3.4.0.data/scripts/telomerecat
telomerecat-3.4.0.dist-info/LICENSE
telomerecat-3.4.0.dist-info/METADATA
telomerecat-3.4.0.dist-info/WHEEL
telomerecat-3.4.0.dist-info/top_level.txt
telomerecat-3.4.0.dist-info/RECORD
