Metadata-Version: 2.1
Name: telomerecat
Version: 3.4.0
Summary: Telomere Computational Analysis Tool
Home-page: UNKNOWN
Author: JHR Farmery
Author-email: cgphelp@sanger.ac.uk
License: GPL
Platform: UNKNOWN
Requires-Python: >= 3.6
Requires-Dist: parabam (>=2.3.0)
Requires-Dist: numpy
Requires-Dist: pysam
Requires-Dist: pandas
